shtk/Job.py
shtk/PipelineNode.py
shtk/PipelineNodeFactory.py
shtk/Shell.py
shtk/Stream.py
shtk/StreamFactory.py
shtk/_AsyncUtil.py
shtk/__init__.py
shtk/_version.py
shtk/util.py
shtk-0.9.7.dist-info/LICENSE
shtk-0.9.7.dist-info/METADATA
shtk-0.9.7.dist-info/WHEEL
shtk-0.9.7.dist-info/top_level.txt
shtk-0.9.7.dist-info/RECORD
