Metadata-Version: 2.1
Name: shtk
Version: 0.9.7
Summary: Shell ToolKit (SHTK)
Home-page: UNKNOWN
Author: Jon Roose
Author-email: jroose@gmail.com
Maintainer: Jon Roose
Maintainer-email: jroose@gmail.com
License: BSD 3-Clause License
Keywords: shell subprocess
Platform: UNKNOWN
Classifier: License :: OSI Approved :: BSD License
Classifier: Programming Language :: Python :: 3
Provides-Extra: test
Requires-Dist: coverage ; extra == 'test'
